README
setup.py
keras_cli/__init__.py
keras_cli/__main__.py
keras_cli.egg-info/PKG-INFO
keras_cli.egg-info/SOURCES.txt
keras_cli.egg-info/dependency_links.txt
keras_cli.egg-info/entry_points.txt
keras_cli.egg-info/requires.txt
keras_cli.egg-info/top_level.txt