Metadata-Version: 1.0
Name: keras-cli
Version: 0.0.1
Summary: Keras command line client
Home-page: https://github.com/paulfitz/keras_cli
Author: Paul Fitzpatrick
Author-email: paulfitz@alum.mit.edu
License: UNKNOWN
Platform: UNKNOWN
